README.md
setup.py
flask_batch/__init__.py
flask_batch/client.py
flask_batch/flask_batch.py
flask_batch/polyfill-bak.py
flask_batch/polyfill.py
flask_batch/py2.py
flask_batch.egg-info/PKG-INFO
flask_batch.egg-info/SOURCES.txt
flask_batch.egg-info/dependency_links.txt
flask_batch.egg-info/requires.txt
flask_batch.egg-info/top_level.txt