Metadata-Version: 1.1
Name: flask-batch
Version: 0.0.1
Summary: UNKNOWN
Home-page: https://github.com/dtkav/flask-batch
Author: Daniel Grossmann-Kavanagh
Author-email: me@danielgk.com
License: MIT
Platform: UNKNOWN
Classifier: Development Status :: 4 - Beta
Classifier: Intended Audience :: Developers
Classifier: Topic :: Software Development :: Libraries :: Python Modules
Classifier: Operating System :: OS Independent
Classifier: Programming Language :: Python :: 2.7
Classifier: Programming Language :: Python :: 3.4
Classifier: Programming Language :: Python :: 3.5
Classifier: Programming Language :: Python :: 3.6
